pmcgrab/__init__.py
pmcgrab/__main__.py
pmcgrab/bioc.py
pmcgrab/constants.py
pmcgrab/fetch.py
pmcgrab/figure.py
pmcgrab/http_utils.py
pmcgrab/idconvert.py
pmcgrab/litctxp.py
pmcgrab/model.py
pmcgrab/oa_service.py
pmcgrab/oai.py
pmcgrab/parser.py
pmcgrab/processing.py
pmcgrab/utils.py
pmcgrab/application/__init__.py
pmcgrab/application/paper_builder.py
pmcgrab/application/processing.py
pmcgrab/application/parsing/__init__.py
pmcgrab/application/parsing/content.py
pmcgrab/application/parsing/contributors.py
pmcgrab/application/parsing/metadata.py
pmcgrab/application/parsing/sections.py
pmcgrab/cli/__init__.py
pmcgrab/cli/pmcgrab_cli.py
pmcgrab/common/__init__.py
pmcgrab/common/html_cleaning.py
pmcgrab/common/serialization.py
pmcgrab/common/xml_processing.py
pmcgrab/domain/__init__.py
pmcgrab/domain/value_objects.py
pmcgrab/infrastructure/__init__.py
pmcgrab/infrastructure/settings.py
pmcgrab-0.5.8.dist-info/METADATA
pmcgrab-0.5.8.dist-info/WHEEL
pmcgrab-0.5.8.dist-info/entry_points.txt
pmcgrab-0.5.8.dist-info/licenses/LICENSE
pmcgrab-0.5.8.dist-info/RECORD
