Metadata-Version: 2.4
Name: pmcgrab
Version: 0.5.8
Summary: AI-ready retrieval and parsing of PubMed Central articles for RAG applications. Install with uv for best performance.
Project-URL: Homepage, https://github.com/rajdeepmondaldotcom/pmcgrab
Project-URL: Documentation, https://github.com/rajdeepmondaldotcom/pmcgrab#readme
Project-URL: Repository, https://github.com/rajdeepmondaldotcom/pmcgrab.git
Project-URL: Issues, https://github.com/rajdeepmondaldotcom/pmcgrab/issues
Project-URL: Changelog, https://github.com/rajdeepmondaldotcom/pmcgrab/releases
Project-URL: Bug Reports, https://github.com/rajdeepmondaldotcom/pmcgrab/issues
Project-URL: Source Code, https://github.com/rajdeepmondaldotcom/pmcgrab
Project-URL: Download, https://pypi.org/project/pmcgrab/
Author-email: Rajdeep Mondal <rajdeep@rajdeepmondal.com>
Maintainer-email: Rajdeep Mondal <rajdeep@rajdeepmondal.com>
License-Expression: Apache-2.0
License-File: LICENSE
Keywords: ai,bioinformatics,entrez,fast,llm,modern,ncbi,pmc,pubmed,rag,research papers,retrieval augmented generation,scientific literature,text mining,uv,xml parsing
Classifier: Development Status :: 4 - Beta
Classifier: Environment :: Console
Classifier: Intended Audience :: Developers
Classifier: Intended Audience :: Science/Research
Classifier: License :: OSI Approved :: Apache Software License
Classifier: Natural Language :: English
Classifier: Operating System :: OS Independent
Classifier: Programming Language :: Python :: 3
Classifier: Programming Language :: Python :: 3.10
Classifier: Programming Language :: Python :: 3.11
Classifier: Programming Language :: Python :: 3.12
Classifier: Programming Language :: Python :: 3.13
Classifier: Topic :: Scientific/Engineering :: Bio-Informatics
Classifier: Topic :: Scientific/Engineering :: Information Analysis
Classifier: Topic :: Software Development :: Libraries :: Python Modules
Classifier: Topic :: Text Processing :: Linguistic
Classifier: Topic :: Text Processing :: Markup :: XML
Requires-Python: >=3.10
Requires-Dist: beautifulsoup4>=4.13.4
Requires-Dist: biopython>=1.83
Requires-Dist: certifi>=2024.0.0
Requires-Dist: html5lib>=1.1
Requires-Dist: ipykernel>=6.30.0
Requires-Dist: jinja2>=3.1.0
Requires-Dist: lxml>=4.9.0
Requires-Dist: numpy>=1.24.0
Requires-Dist: pandas>=2.0.0
Requires-Dist: requests>=2.28.0
Requires-Dist: tqdm>=4.64.0
Provides-Extra: dev
Requires-Dist: bandit[toml]>=1.7.0; extra == 'dev'
Requires-Dist: build>=0.10.0; extra == 'dev'
Requires-Dist: mypy>=1.5.0; extra == 'dev'
Requires-Dist: pre-commit>=3.0.0; extra == 'dev'
Requires-Dist: pytest-cov>=4.0.0; extra == 'dev'
Requires-Dist: pytest-xdist>=3.0.0; extra == 'dev'
Requires-Dist: pytest>=7.0.0; extra == 'dev'
Requires-Dist: ruff>=0.1.0; extra == 'dev'
Requires-Dist: safety>=2.0.0; extra == 'dev'
Requires-Dist: twine>=4.0.0; extra == 'dev'
Provides-Extra: docs
Requires-Dist: mkdocs-material>=9.5.8; extra == 'docs'
Requires-Dist: mkdocs>=1.5.0; extra == 'docs'
Requires-Dist: mkdocstrings[python]>=0.20.0; extra == 'docs'
Provides-Extra: test
Requires-Dist: pytest-cov>=4.0.0; extra == 'test'
Requires-Dist: pytest-xdist>=3.0.0; extra == 'test'
Requires-Dist: pytest>=7.0.0; extra == 'test'
Requires-Dist: responses>=0.23.0; extra == 'test'
